daemon/__init__.py
daemon/daemon.py
daemon_process-0.9.2.dist-info/LICENSE.txt
daemon_process-0.9.2.dist-info/METADATA
daemon_process-0.9.2.dist-info/WHEEL
daemon_process-0.9.2.dist-info/top_level.txt
daemon_process-0.9.2.dist-info/RECORD
