Metadata-Version: 2.1
Name: daemon-process
Version: 0.9.2
Summary: The package for running daemonized processes
Home-page: https://github.com/J4CKVVH173/python-daemonization.git
Author: J4CK VVH173
Author-email: p78901234567890@gmail.com
License: UNKNOWN
Platform: UNKNOWN
Classifier: Programming Language :: Python :: 3
Classifier: License :: OSI Approved :: Python Software Foundation License
Classifier: Operating System :: Unix
Requires-Python: >=3
